pycmds/__init__.py
pycmds/completer.py
pycmds/core.py
pycmds/extratypes.py
pycmds/utils.py
pycmds-1.0.4.dist-info/METADATA
pycmds-1.0.4.dist-info/RECORD
pycmds-1.0.4.dist-info/WHEEL
pycmds-1.0.4.dist-info/top_level.txt
